pdfeaturegen
