Metadata-Version: 1.0
Name: pdfeaturegen
Version: 0.0.3
Summary: Supporting functions to generate features in Pandas Dataframe for Machine Learning
Home-page: https://github.com/ivanfoong/pdfeaturegen
Author: Ivan Foong
Author-email: vonze21@gmail.com
License: MIT
Platform: UNKNOWN
